papertraillogger/__init__.py
papertraillogger/papertrail_logger.py
papertraillogger-0.0.4.dist-info/LICENSE
papertraillogger-0.0.4.dist-info/METADATA
papertraillogger-0.0.4.dist-info/WHEEL
papertraillogger-0.0.4.dist-info/top_level.txt
papertraillogger-0.0.4.dist-info/RECORD
