Metadata-Version: 2.1
Name: papertraillogger
Version: 0.0.4
Summary: a papertrail logging wrapper
Home-page: https://github.com/Wasp971/papertrail_logger
Author: Mirco Gnuva
Author-email: UNKNOWN
License: MIT
Keywords: papertrail,logging, logger
Platform: UNKNOWN
